[
  {"name": "Il Mannarino – Alassio, Via Brennero 4",                    "email": "alassio@ilmannarino.it"},
  {"name": "Il Mannarino – Alessandria, Via dei Martiri 14",            "email": "alessandria@ilmannarino.it"},
  {"name": "Il Mannarino – Arcore, Via Antonio Casati 80",              "email": "arcore@ilmannarino.it"},
  {"name": "Il Mannarino – Bergamo, Viale Papa Giovanni XXIII 66",      "email": "bergamo@ilmannarino.it"},
  {"name": "Il Mannarino – Brescia, Via Tosio 3",                       "email": "brescia@ilmannarino.it"},
  {"name": "Il Mannarino – Busto Arsizio, Piazza Vittorio Emanuele II", "email": "busto@ilmannarino.it"},
  {"name": "Il Mannarino – Como, Piazza Giovanni Amendola 11",          "email": "como@ilmannarino.it"},
  {"name": "Il Mannarino – Genova, Via Domenico Fiasella 31",           "email": "genova@ilmannarino.it"},
  {"name": "Il Mannarino – Milano, Alzaia Naviglio Grande 2",           "email": "navigli@ilmannarino.it"},
  {"name": "Il Mannarino – Milano, Piazza de Angeli 1",                 "email": "deangeli@ilmannarino.it"},
  {"name": "Il Mannarino – Milano, Via Carlo Tenca 12",                 "email": "tenca@ilmannarino.it"},
  {"name": "Il Mannarino – Milano, Via Galvano Fiamma 6",               "email": "fiamma@ilmannarino.it"},
  {"name": "Il Mannarino – Milano, Via Daimler 61",                     "email": "merlata@ilmannarino.it"},
  {"name": "Il Mannarino – Modena, Via Del Taglio 59",                  "email": "modena@ilmannarino.it"},
  {"name": "Il Mannarino – Novara, Piazza Martiri della Libertà 5",     "email": "novara@ilmannarino.it"},
  {"name": "Il Mannarino – Reggio Emilia, Piazza XXIV Maggio 2/C",      "email": "reggioemilia@ilmannarino.it"},
  {"name": "Il Mannarino – Saronno, Via Luigi Lazzaroni 25",            "email": "saronno@ilmannarino.it"},
  {"name": "Il Mannarino – Seregno, Via Cadore 96",                     "email": "seregno@ilmannarino.it"},
  {"name": "Il Mannarino – Torino, Via della Rocca 4",                  "email": "torino@ilmannarino.it"},
  {"name": "Il Mannarino – Torino, Via IV Marzo 12",                    "email": "torino4marzo@ilmannarino.it"},
  {"name": "Il Mannarino – Varese, Via Giuseppe Bolchini 15",           "email": "varese@ilmannarino.it"},
  {"name": "Il Mannarino – Verona, Via Pellicciai 20",                  "email": "verona@ilmannarino.it"}
]
